{
  "__type__": "cc.JsonAsset",
  "_name": "moon8",
  "_objFlags": 0,
  "_native": "",
  "json": {
    "path": [
      {
        "centerPos": {
          "x": 283,
          "y": 374
        },
        "startPos": {
          "x": 147,
          "y": 458
        },
        "endPos": {
          "x": 418,
          "y": 290
        },
        "blockSize": {
          "wid": 270,
          "hei": 168
        }
      },
      {
        "centerPos": {
          "x": 548,
          "y": 216
        },
        "startPos": {
          "x": 490,
          "y": 338
        },
        "endPos": {
          "x": 606,
          "y": 93
        },
        "blockSize": {
          "wid": 115,
          "hei": 244
        }
      },
      {
        "centerPos": {
          "x": 562,
          "y": -192
        },
        "startPos": {
          "x": 509,
          "y": -115
        },
        "endPos": {
          "x": 615,
          "y": -270
        },
        "blockSize": {
          "wid": 105,
          "hei": 155
        }
      },
      {
        "centerPos": {
          "x": 427,
          "y": -388
        },
        "startPos": {
          "x": 331,
          "y": -317
        },
        "endPos": {
          "x": 524,
          "y": -459
        },
        "blockSize": {
          "wid": 193,
          "hei": 142
        }
      },
      {
        "centerPos": {
          "x": -2,
          "y": -366
        },
        "startPos": {
          "x": -93,
          "y": -307
        },
        "endPos": {
          "x": 89,
          "y": -425
        },
        "blockSize": {
          "wid": 181,
          "hei": 118
        }
      },
      {
        "centerPos": {
          "x": -471,
          "y": -414
        },
        "startPos": {
          "x": -329,
          "y": -368
        },
        "endPos": {
          "x": -614,
          "y": -459
        },
        "blockSize": {
          "wid": 285,
          "hei": 90
        }
      },
      {
        "centerPos": {
          "x": -320,
          "y": -209
        },
        "startPos": {
          "x": -380,
          "y": -128
        },
        "endPos": {
          "x": -260,
          "y": -289
        },
        "blockSize": {
          "wid": 120,
          "hei": 161
        }
      },
      {
        "centerPos": {
          "x": -2,
          "y": -132
        },
        "startPos": {
          "x": -72,
          "y": -69
        },
        "endPos": {
          "x": 68,
          "y": -195
        },
        "blockSize": {
          "wid": 140,
          "hei": 125
        }
      },
      {
        "centerPos": {
          "x": -567,
          "y": -31
        },
        "startPos": {
          "x": -521,
          "y": 60
        },
        "endPos": {
          "x": -614,
          "y": -122
        },
        "blockSize": {
          "wid": 93,
          "hei": 181
        }
      },
      {
        "centerPos": {
          "x": 265,
          "y": -135
        },
        "startPos": {
          "x": 196,
          "y": -66
        },
        "endPos": {
          "x": 333,
          "y": -204
        },
        "blockSize": {
          "wid": 137,
          "hei": 137
        }
      }
    ]
  }
}